README.rst
setup.py
midict/__init__.py
midict.egg-info/PKG-INFO
midict.egg-info/SOURCES.txt
midict.egg-info/dependency_links.txt
midict.egg-info/top_level.txt
midict.egg-info/zip-safe