Metadata-Version: 1.1
Name: midict
Version: 0.1.2
Summary: MIDict is an ordered "dictionary" with multiple indices where any index can serve as "keys" or "values", capable of assessing multiple values via its powerful indexing syntax, and suitable as a bidirectional/inverse dict (a drop-in replacement for dict/OrderedDict in Python 2 & 3).
Home-page: https://github.com/ShenggaoZhu/midict
Author: Shenggao Zhu
Author-email: zshgao@gmail.com
License: MIT
Keywords: dict,dictionary,mapping,bidirectional,bijective,two-way,double,inverse,reverse,multiple,index,multiple indices,multiple values,multiple keys,MIMapping,MIDict,FrozenMIDict,AttrDict,IndexDict,multi-indexing syntax
Platform: UNKNOWN
Classifier: Development Status :: 4 - Beta
Classifier: Intended Audience :: Developers
Classifier: License :: OSI Approved :: BSD License
Classifier: Natural Language :: English
Classifier: Operating System :: OS Independent
Classifier: Programming Language :: Python
Classifier: Programming Language :: Python :: 2.7
Classifier: Programming Language :: Python :: 3.3
Classifier: Programming Language :: Python :: 3.4
Classifier: Programming Language :: Python :: 3.5
Classifier: Topic :: Scientific/Engineering :: Mathematics
Classifier: Topic :: Software Development :: Libraries :: Python Modules
